[
  {
    "id": "rec_cmuhs3fqhoq37nmfq6q0",
    "bio": "Fred",
    "bioMediaUrls": "",
    "contactDetails": "fredfredfred",
    "name": "Kurt",
    "profilePicUrl": "https://nmsud-data.nmsassistant.com/img/community/rec_cmuhs3fqhoq37nmfq6q0_profile_pic.png",
    "socials": "https://assistantapps.com",
    "tags": "Civilization"
  },
  {
    "id": "rec_cmuhs3fqhoq37nmfq6q0",
    "bio": "Fred",
    "bioMediaUrls": "",
    "contactDetails": "fredfredfred",
    "name": "Kurt",
    "profilePicUrl": "https://nmsud-data.nmsassistant.com/img/community/rec_cmuhs3fqhoq37nmfq6q0_profile_pic.png",
    "socials": "https://assistantapps.com",
    "tags": "Civilization"
  }
]